Metadata-Version: 1.0
Name: boats.py
Version: 0.1
Summary: API wrapper for discord.boats
Home-page: https://discord.boats
Author: Epic
Author-email: UNKNOWN
License: MIT
Platform: UNKNOWN
